[
  {
    "id": "e9fb8b90-ed04-4f74-8a66-0181f9cc02f7",
    "data": [
      {
        "text": "What\u0027s the next ",
        "userDefined": false
      },
      {
        "text": "ranked mode",
        "alias": "game-mode",
        "meta": "@game-mode",
        "userDefined": false
      },
      {
        "text": "?",
        "userDefined": false
      }
    ],
    "isTemplate": false,
    "count": 0
  },
  {
    "id": "2fcea467-c90e-4547-b7c3-4b0dc55705d4",
    "data": [
      {
        "text": "Show me every upcoming stage for ",
        "userDefined": false
      },
      {
        "text": "league battles",
        "alias": "game-mode",
        "meta": "@game-mode",
        "userDefined": false
      },
      {
        "text": "!",
        "userDefined": false
      }
    ],
    "isTemplate": false,
    "count": 0
  },
  {
    "id": "58949861-1aa9-4efb-8919-a39a42d81785",
    "data": [
      {
        "text": "I want to see all stages for ",
        "userDefined": false
      },
      {
        "text": "league battles",
        "alias": "game-mode",
        "meta": "@game-mode",
        "userDefined": false
      },
      {
        "text": "!",
        "userDefined": false
      }
    ],
    "isTemplate": false,
    "count": 0
  },
  {
    "id": "5ad0fcdc-f316-433a-9ee6-a04f032ef28b",
    "data": [
      {
        "text": "Show me every future stage for ",
        "userDefined": false
      },
      {
        "text": "ranked mode",
        "alias": "game-mode",
        "meta": "@game-mode",
        "userDefined": false
      },
      {
        "text": "!",
        "userDefined": false
      }
    ],
    "isTemplate": false,
    "count": 0
  },
  {
    "id": "faff2b57-c28e-455f-9a73-64f7bf048093",
    "data": [
      {
        "text": "Show me ",
        "userDefined": false
      },
      {
        "text": "all",
        "meta": "@sys.ignore",
        "userDefined": false
      },
      {
        "text": " upcoming maps for ",
        "userDefined": false
      },
      {
        "text": "ranked mode",
        "alias": "game-mode",
        "meta": "@game-mode",
        "userDefined": false
      }
    ],
    "isTemplate": false,
    "count": 0,
    "updated": 1514316857
  }
]